MANIFEST.in
README.md
setup.py
bin/gaode-api-config
bin/gaode-api-intersection
gaode_api_cli/__init__.py
gaode_api_cli/config.json
gaode_api_cli/config.py
gaode_api_cli/intersection.py
gaode_api_cli.egg-info/PKG-INFO
gaode_api_cli.egg-info/SOURCES.txt
gaode_api_cli.egg-info/dependency_links.txt
gaode_api_cli.egg-info/requires.txt
gaode_api_cli.egg-info/top_level.txt